zmipc/__init__.py
zmipc/client.py
zmipc-0.5.dist-info/LICENSE
zmipc-0.5.dist-info/METADATA
zmipc-0.5.dist-info/WHEEL
zmipc-0.5.dist-info/top_level.txt
zmipc-0.5.dist-info/RECORD
